junit_report/__init__.py
junit_report/json_junit_exporter.py
junit_report/utils.py
junit_report/decorators/__init__.py
junit_report/decorators/_junit_decorator.py
junit_report/decorators/_junit_fixture_test_case.py
junit_report/decorators/_junit_test_case.py
junit_report/decorators/_junit_test_suite.py
junit_report-0.2.7.dist-info/LICENSE
junit_report-0.2.7.dist-info/METADATA
junit_report-0.2.7.dist-info/WHEEL
junit_report-0.2.7.dist-info/top_level.txt
junit_report-0.2.7.dist-info/RECORD
