Metadata-Version: 2.1
Name: junit-report
Version: 0.2.7
Summary: Export your test suites and cases to JUnit report using decorators
Home-page: https://github.com/eliorerz/junit-report
Author: Elior Erez
Author-email: elior123@gmail.com
License: MIT
Platform: UNKNOWN
Classifier: Development Status :: 3 - Alpha
Classifier: License :: OSI Approved :: MIT License
Classifier: Operating System :: OS Independent
Classifier: Programming Language :: Python
Classifier: Programming Language :: Python :: 3
Classifier: Programming Language :: Python :: 3.7
Classifier: Programming Language :: Python :: 3.8
Classifier: Programming Language :: Python :: 3.9
Classifier: Topic :: Software Development :: Build Tools
Classifier: Topic :: Software Development :: Testing
Requires-Python: >=3.7.0
License-File: LICENSE
Requires-Dist: pytest (>=7.0.0)
Requires-Dist: decorator (>=5.1.1)
Requires-Dist: junit-xml (==1.9)
